{
  "parent": "minecraft:recipes/root",
  "criteria": {
    "has_the_recipe": {
      "conditions": {
        "recipe": "tutorial-mod:zircon_shovel"
      },
      "trigger": "minecraft:recipe_unlocked"
    },
    "has_tutorial-mod.zircon": {
      "conditions": {
        "items": [
          {
            "items": "tutorial-mod:zircon"
          }
        ]
      },
      "trigger": "minecraft:inventory_changed"
    }
  },
  "requirements": [
    [
      "has_the_recipe",
      "has_tutorial-mod.zircon"
    ]
  ],
  "rewards": {
    "recipes": [
      "tutorial-mod:zircon_shovel"
    ]
  }
}